spam/__init__.py
spam/datasets.py
spam/errors.py
spam/DIC/__init__.py
spam/DIC/_correlateLL.py
spam/DIC/ddic.py
spam/DIC/deform.py
spam/DIC/globalDVC.py
spam/DIC/grid.py
spam/DIC/kinematics.py
spam/DIC/ldic.py
spam/DIC/multimodal.py
spam/DIC/pixelSearch.py
spam/DIC/registration.py
spam/data/placeholder.txt
spam/data/DEM/SpheresMMR.txt
spam/data/DEM/contacts.txt
spam/data/DEM/spheres.txt
spam/data/DEM/uniformSpheres.txt
spam/data/concrete/concrete_neutron-bin16.tif
spam/data/concrete/concrete_x-ray-bin16.tif
spam/data/mesh/structuredMesh.p
spam/data/mesh/unstructuredMesh.p
spam/data/snow/snow.tif
spam/deformation/__init__.py
spam/deformation/deformationField.py
spam/deformation/deformationFunction.py
spam/excursions/__init__.py
spam/excursions/elkc.py
spam/excursions/randomFields.py
spam/filters/__init__.py
spam/filters/distanceField.py
spam/filters/morphologicalOperations.py
spam/filters/movingFilters.py
spam/helpers/__init__.py
spam/helpers/histogramTools.py
spam/helpers/imageManipulation.py
spam/helpers/optionsParser.py
spam/helpers/test.py
spam/helpers/tsvio.py
spam/helpers/vtkio.py
spam/kalisphera/__init__.py
spam/kalisphera/kalisphera.py
spam/kalisphera/spheroid.py
spam/label/ITKwatershed.py
spam/label/__init__.py
spam/label/contacts.py
spam/label/label.py
spam/measurements/__init__.py
spam/measurements/covariance.py
spam/measurements/globalDescriptors.py
spam/measurements/porosityField.py
spam/mesh/__init__.py
spam/mesh/objects.py
spam/mesh/projection.py
spam/mesh/structured.py
spam/mesh/tetrahedra.py
spam/mesh/unstructured.py
spam/orientations/__init__.py
spam/orientations/analyse.py
spam/orientations/generate.py
spam/plotting/__init__.py
spam/plotting/greyLevelHistogram.py
spam/plotting/multivariateGaussians.py
spam/plotting/orientationPlotter.py
spam/plotting/particleSizeDistribution.py
spam/plotting/tetrahedraPlotter.py
spam/scripts/ddic.py
spam/scripts/deformImage.py
spam/scripts/discreteStrain.py
spam/scripts/ereg.py
spam/scripts/ereg_discrete.py
spam-0.8.1.3.dist-info/licenses/LICENSE.md
spam-0.8.1.3.dist-info/METADATA
spam-0.8.1.3.dist-info/WHEEL
spam-0.8.1.3.dist-info/entry_points.txt
spam-0.8.1.3.dist-info/top_level.txt
spam-0.8.1.3.dist-info/RECORD
