Metadata-Version: 2.4
Name: spam
Version: 0.8.1.3
Summary: Software for the Practical Analysis of Materials
Author-email: Edward Andò <edward.ando@epfl.ch>, Emmanuel Roubin <emmanuel.roubin@univ-grenoble-alpes.fr>, Gustavo Pinzón <gustavo.pinzon-forero@esrf.fr>, Olga Stamati <olga.stamati@univ-grenoble-alpes.fr>
Maintainer-email: Edward Andò <edward.ando@epfl.ch>, Emmanuel Roubin <emmanuel.roubin@univ-grenoble-alpes.fr>, Gustavo Pinzón <gustavo.pinzon-forero@esrf.fr>, Olga Stamati <olga.stamati@univ-grenoble-alpes.fr>
License-Expression: GPL-3.0-or-later
Project-URL: Homepage, https://spam-project.dev
Project-URL: Documentation, https://spam-project.dev/docs/
Project-URL: Repository, https://gitlab.com/spam-project/spam
Keywords: digital volume correlation,digital image correlation,registration,multimodal registration,strain calculation,label analysis,image analysis,random fields,synthetic images
Classifier: Development Status :: 4 - Beta
Classifier: Environment :: Console
Classifier: Intended Audience :: Science/Research
Classifier: Operating System :: POSIX :: Linux
Classifier: Programming Language :: Python :: 3
Classifier: Programming Language :: Python :: 3.9
Classifier: Programming Language :: Python :: 3.10
Classifier: Programming Language :: Python :: 3.11
Classifier: Programming Language :: Python :: 3.12
Classifier: Programming Language :: Python :: 3 :: Only
Classifier: Topic :: Scientific/Engineering :: Image Recognition
Classifier: Topic :: Scientific/Engineering :: Mathematics
Requires-Python: >=3.9
License-File: LICENSE.md
Requires-Dist: wheel>=0.22
Requires-Dist: numpy>=1.26.0
Requires-Dist: scipy>=1.11
Requires-Dist: scikit-image>=0.17.2
Requires-Dist: tifffile>=2020.8.25
Requires-Dist: matplotlib>=3.3.4
Requires-Dist: SimpleITK>=2.0.2
Requires-Dist: progressbar>=2.5
Requires-Dist: python-decouple>=3.4
Requires-Dist: gmsh>=4.9.3
Requires-Dist: meshio>=4.3.11
Requires-Dist: h5py>=3.1.0
Requires-Dist: pyyaml
Requires-Dist: numba
Requires-Dist: pyamg>=4.0.0
Requires-Dist: gstools>=1.5.1
Requires-Dist: spambind>=0.8
Provides-Extra: dev
Requires-Dist: pip-tools; extra == "dev"
Requires-Dist: docutils>=0.16; extra == "dev"
Requires-Dist: Jinja2>=3.0.3; extra == "dev"
Requires-Dist: pre-commit; extra == "dev"
Requires-Dist: pytest>=3.6; extra == "dev"
Requires-Dist: pytest-cov[all]; extra == "dev"
Requires-Dist: pytest-xdist; extra == "dev"
Provides-Extra: docs
Requires-Dist: coverage[toml]>=5.5; extra == "docs"
Requires-Dist: sphinx>=4.5.0; extra == "docs"
Requires-Dist: sphinx-gallery>=0.8.2; extra == "docs"
Requires-Dist: sphinx-book-theme; extra == "docs"
Requires-Dist: sphinx-copybutton; extra == "docs"
Requires-Dist: sphinx-pyproject; extra == "docs"
Requires-Dist: sphinx-design; extra == "docs"
Provides-Extra: graphical
Requires-Dist: PyQt5>=5.14.2; extra == "graphical"
Requires-Dist: qimage2ndarray>=1.8.3; extra == "graphical"
Provides-Extra: all
Requires-Dist: spam[dev,docs,graphical]; extra == "all"
Dynamic: license-file
